gppc/__description__.py
gppc/__init__.py
gppc/__main__.py
gppc/__version__.py
gppc/_constant.py
gppc/_db.py
gppc/_db_old.py
gppc/_display.py
gppc/_gppc.py
gppc/_item.py
gppc-0.1.12.dist-info/LICENSE.txt
gppc-0.1.12.dist-info/METADATA
gppc-0.1.12.dist-info/WHEEL
gppc-0.1.12.dist-info/entry_points.txt
gppc-0.1.12.dist-info/top_level.txt
gppc-0.1.12.dist-info/RECORD
