Metadata-Version: 2.2
Name: gppc
Version: 0.1.12
Summary: Check OSRS Grand Exchange prices from the command line. Includes module functionality to check and save item price history.
Home-page: https://pypi.org/project/gppc/
Author: moxxos
Author-email: moxxos@proton.me
License: GNU AGPLv3
Project-URL: Source, https://github.com/moxxos/gppc
Keywords: OSRS,Grand Exchange,GrandExchange,GE,OSRS Grand Exchange,Runescape,Oldschool Runescape,Old School Runescape,OS Runescape
Classifier: Programming Language :: Python :: 3
Requires-Python: <=3.14,>=3.8
License-File: LICENSE.txt
Requires-Dist: requests
Requires-Dist: climage
Requires-Dist: platformdirs
Requires-Dist: pandas
Provides-Extra: dev
Requires-Dist: autopep8>=1.7.0; extra == "dev"
Requires-Dist: flake8>=5.0.4; extra == "dev"
Requires-Dist: pylint>=2.15.2; extra == "dev"
Requires-Dist: sphinx>=5.3.0; extra == "dev"
Dynamic: description
Dynamic: description-content-type
Dynamic: home-page
Dynamic: project-url
Dynamic: summary
